README.md
setup.py
barin/__init__.py
barin/adapter.py
barin/base.py
barin/collection.py
barin/cursor.py
barin/errors.py
barin/event.py
barin/field.py
barin/index.py
barin/metadata.py
barin/mql.py
barin/numeric.py
barin/query.py
barin/util.py
barin.egg-info/PKG-INFO
barin.egg-info/SOURCES.txt
barin.egg-info/dependency_links.txt
barin.egg-info/entry_points.txt
barin.egg-info/not-zip-safe
barin.egg-info/top_level.txt
barin/manager/__init__.py
barin/manager/class_manager.py
barin/manager/instance_manager.py
barin/manager/manager.py
barin/manager/polymorphism.py
barin/schema/__init__.py
barin/schema/base.py
barin/schema/compiler.py
barin/schema/compound.py
barin/schema/scalar.py
barin/tests/__init__.py
barin/tests/test_collection.py
barin/tests/test_derived.py
barin/tests/test_fields.py
barin/tests/test_hooks.py
barin/tests/test_manager.py
barin/tests/test_mql.py
barin/tests/test_schema.py