Metadata-Version: 1.1
Name: barin
Version: 0.0.5.dev56
Summary: Barin, yet another MongoDB schema validation layer
Home-page: UNKNOWN
Author: Rick Copeland
Author-email: rick@arborian.com
License: UNKNOWN
Platform: UNKNOWN
Classifier: Programming Language :: Python
